tiktok_uploader/__init__.py
tiktok_uploader/auth.py
tiktok_uploader/cli.py
tiktok_uploader/exceptions.py
tiktok_uploader/uploader.py
simple_tiktok_uploader-0.2.0.dist-info/METADATA
simple_tiktok_uploader-0.2.0.dist-info/WHEEL
simple_tiktok_uploader-0.2.0.dist-info/entry_points.txt
simple_tiktok_uploader-0.2.0.dist-info/licenses/LICENSE
simple_tiktok_uploader-0.2.0.dist-info/RECORD
