Metadata-Version: 2.4
Name: simple-tiktok-uploader
Version: 0.2.0
Summary: Simple TikTok video uploader using Playwright - no API key required
Project-URL: Homepage, https://github.com/YanivGabay/tiktok-uploader
Project-URL: Repository, https://github.com/YanivGabay/tiktok-uploader
Project-URL: Issues, https://github.com/YanivGabay/tiktok-uploader/issues
Author: Yaniv Gabay
License-Expression: MIT
License-File: LICENSE
Keywords: automation,playwright,tiktok,upload,video
Classifier: Development Status :: 4 - Beta
Classifier: Intended Audience :: Developers
Classifier: License :: OSI Approved :: MIT License
Classifier: Operating System :: OS Independent
Classifier: Programming Language :: Python :: 3
Classifier: Programming Language :: Python :: 3.9
Classifier: Programming Language :: Python :: 3.10
Classifier: Programming Language :: Python :: 3.11
Classifier: Programming Language :: Python :: 3.12
Classifier: Topic :: Internet
Classifier: Topic :: Multimedia :: Video
Requires-Python: >=3.9
Requires-Dist: playwright>=1.40.0
Provides-Extra: dev
Requires-Dist: mypy>=1.0.0; extra == 'dev'
Requires-Dist: pytest-cov>=4.0.0; extra == 'dev'
Requires-Dist: pytest>=7.0.0; extra == 'dev'
Requires-Dist: ruff>=0.1.0; extra == 'dev'
